pulseplot/__init__.py
pulseplot/parse.py
pulseplot/pulseplot.py
pulseplot-0.1.dist-info/LICENSE.md
pulseplot-0.1.dist-info/METADATA
pulseplot-0.1.dist-info/WHEEL
pulseplot-0.1.dist-info/top_level.txt
pulseplot-0.1.dist-info/RECORD
