Metadata-Version: 2.1
Name: pulseplot
Version: 0.1
Summary: A module to draw pulse-timing diagrams using Python/Matplotlib
Home-page: https://github.com/kaustubhmote/pulseplot
Author: Kaustubh R. Mote
Author-email: kaustubh@gmail.com
License: UNKNOWN
Platform: UNKNOWN
Classifier: Intended Audience :: Science/Research
Classifier: Intended Audience :: Developers
Classifier: License :: OSI Approved :: BSD License
Classifier: Natural Language :: English
Classifier: Programming Language :: Python :: 3.7
Classifier: Programming Language :: Python :: 3.8
Classifier: Programming Language :: Python :: 3.9
Classifier: Topic :: Scientific/Engineering
Classifier: Operating System :: MacOS :: MacOS X
Classifier: Operating System :: Microsoft :: Windows
Classifier: Operating System :: POSIX :: Linux
Requires-Python: >=3.7
Requires-Dist: numpy
Requires-Dist: matplotlib
